qmm/__init__.py
qmm/core/__init__.py
qmm/core/helper.py
qmm/core/prediction.py
qmm/core/press.py
qmm/core/stability.py
qmm/core/structure.py
qmm/extensions/__init__.py
qmm/extensions/effects.py
qmm/extensions/indicators.py
qmm/extensions/life.py
qmm/extensions/paths.py
qmm/extensions/senstability.py
qmm/extensions/validation.py
qmm_core-0.4.6.dist-info/METADATA
qmm_core-0.4.6.dist-info/WHEEL
qmm_core-0.4.6.dist-info/licenses/LICENSE
qmm_core-0.4.6.dist-info/RECORD
