Metadata-Version: 2.4
Name: qmm-core
Version: 0.4.6
Summary: A software platform for analysing the structure and function of complex systems
Project-URL: Homepage, https://github.com/jaydenhyman/qmm
Project-URL: Bug Tracker, https://github.com/jaydenhyman/qmm/issues
Author-email: Jayden Hyman <j.hyman@uq.edu.au>
License-File: LICENSE
Classifier: Development Status :: 3 - Alpha
Classifier: Intended Audience :: Science/Research
Classifier: License :: OSI Approved :: BSD License
Classifier: Programming Language :: Python :: 3.9
Classifier: Programming Language :: Python :: 3.10
Classifier: Programming Language :: Python :: 3.11
Classifier: Programming Language :: Python :: 3.12
Requires-Python: >=3.9
Requires-Dist: networkx>=3.1
Requires-Dist: numpy<2.0.0,>=1.24.3
Requires-Dist: pandas>=2.0.3
Requires-Dist: sympy>=1.12.0
Requires-Dist: thewalrus>=0.21.0
Provides-Extra: dev
Requires-Dist: pytest; extra == 'dev'
Requires-Dist: ruff; extra == 'dev'
Provides-Extra: docs
Requires-Dist: mkdocs-autorefs; extra == 'docs'
Requires-Dist: mkdocs-jupyter; extra == 'docs'
Requires-Dist: mkdocs-material>=9.5.0; extra == 'docs'
Requires-Dist: mkdocs>=1.5.0; extra == 'docs'
Requires-Dist: mkdocstrings[python]>=0.24.0; extra == 'docs'
Requires-Dist: ruff; extra == 'docs'
